equinox_mcp/__init__.py
equinox_mcp/__main__.py
equinox_mcp/docs_source.py
equinox_mcp/server.py
equinox_mcp/prompts/__init__.py
equinox_mcp/prompts/equinox_task.py
equinox_mcp/resources/__init__.py
equinox_mcp/tools/__init__.py
equinox_mcp/tools/equinox_checker.py
equinox_mcp/tools/get_documentation.py
equinox_mcp/tools/list_sections.py
equinox_mcp-0.1.1.dist-info/METADATA
equinox_mcp-0.1.1.dist-info/WHEEL
equinox_mcp-0.1.1.dist-info/entry_points.txt
equinox_mcp-0.1.1.dist-info/RECORD
